summary.py
git_commit_summary-1.0.1.dist-info/METADATA
git_commit_summary-1.0.1.dist-info/WHEEL
git_commit_summary-1.0.1.dist-info/entry_points.txt
git_commit_summary-1.0.1.dist-info/top_level.txt
git_commit_summary-1.0.1.dist-info/RECORD
