Metadata-Version: 2.4
Name: git-commit-summary
Version: 1.0.1
Summary: A powerful CLI tool to summarize git commits with rich visual feedback.
Home-page: https://github.com/otaku0304/git-commit-summary
Author: Sai Annam
Author-email: contact@mraskchay.com
Classifier: Programming Language :: Python :: 3
Classifier: License :: OSI Approved :: MIT License
Classifier: Operating System :: OS Independent
Classifier: Environment :: Console
Classifier: Topic :: Software Development :: Version Control :: Git
Requires-Python: >=3.6
Requires-Dist: colorama>=0.4.6
Dynamic: author
Dynamic: author-email
Dynamic: classifier
Dynamic: description
Dynamic: description-content-type
Dynamic: home-page
Dynamic: requires-dist
Dynamic: requires-python
Dynamic: summary
